Metadata-Version: 2.1
Name: colout
Version: 0.12.1
Summary: Color Up Arbitrary Command Output.
Home-page: http://nojhan.github.com/colout/
Author: nojhan
Author-email: nojhan@nojhan.net
License: GPLv3
Platform: UNKNOWN
Classifier: Environment :: Console
Classifier: Development Status :: 5 - Production/Stable
Classifier: License :: OSI Approved :: GNU General Public License v3 (GPLv3)
Classifier: Operating System :: POSIX
Classifier: Operating System :: POSIX :: Linux
Classifier: Programming Language :: Python :: 3 :: Only
Classifier: Programming Language :: Python :: 3.5
Classifier: Programming Language :: Python :: 3.6
Classifier: Programming Language :: Python :: 3.7
Classifier: Programming Language :: Python :: 3.8
Classifier: Topic :: Utilities
Classifier: Topic :: Text Processing
Classifier: Topic :: Text Processing :: Filters
Requires-Python: >=3.5
Requires-Dist: pygments
Requires-Dist: babel
